Scapy24ZhongwenWendang/README.md
Scapy24ZhongwenWendang/__init__.py
Scapy24ZhongwenWendang/__main__.py
Scapy24ZhongwenWendang/file.epub
Scapy24ZhongwenWendang/index.html
Scapy24ZhongwenWendang/css/__init__.py
Scapy24ZhongwenWendang/css/annotations.css
Scapy24ZhongwenWendang/css/main.css
Scapy24ZhongwenWendang/css/normalize.css
Scapy24ZhongwenWendang/css/popup.css
Scapy24ZhongwenWendang/font/__init__.py
Scapy24ZhongwenWendang/font/fontello.eot
Scapy24ZhongwenWendang/font/fontello.svg
Scapy24ZhongwenWendang/font/fontello.ttf
Scapy24ZhongwenWendang/font/fontello.woff
Scapy24ZhongwenWendang/img/__init__.py
Scapy24ZhongwenWendang/img/annotator-glyph-sprite.png
Scapy24ZhongwenWendang/img/annotator-icon-sprite.png
Scapy24ZhongwenWendang/img/apple-touch-icon.png
Scapy24ZhongwenWendang/img/cancelfullscreen.png
Scapy24ZhongwenWendang/img/close.png
Scapy24ZhongwenWendang/img/fullscreen.png
Scapy24ZhongwenWendang/img/loader.gif
Scapy24ZhongwenWendang/img/menu-icon.png
Scapy24ZhongwenWendang/img/save.png
Scapy24ZhongwenWendang/img/saved.png
Scapy24ZhongwenWendang/img/settings-s.png
Scapy24ZhongwenWendang/img/settings.png
Scapy24ZhongwenWendang/img/star.png
Scapy24ZhongwenWendang/js/__init__.py
Scapy24ZhongwenWendang/js/epub.js
Scapy24ZhongwenWendang/js/epub.min.js
Scapy24ZhongwenWendang/js/epub.min.map
Scapy24ZhongwenWendang/js/hooks.min.js
Scapy24ZhongwenWendang/js/hooks.min.map
Scapy24ZhongwenWendang/js/reader.js
Scapy24ZhongwenWendang/js/reader.js.map
Scapy24ZhongwenWendang/js/reader.min.js
Scapy24ZhongwenWendang/js/reader.min.map
Scapy24ZhongwenWendang/js/hooks/__init__.py
Scapy24ZhongwenWendang/js/hooks/extensions/__init__.py
Scapy24ZhongwenWendang/js/hooks/extensions/highlight.js
Scapy24ZhongwenWendang/js/libs/__init__.py
Scapy24ZhongwenWendang/js/libs/jquery.min.js
Scapy24ZhongwenWendang/js/libs/localforage.min.js
Scapy24ZhongwenWendang/js/libs/screenfull.js
Scapy24ZhongwenWendang/js/libs/screenfull.min.js
Scapy24ZhongwenWendang/js/libs/zip.min.js
scapy_2_4_zhongwen_wendang-2024.3.4.0.dist-info/METADATA
scapy_2_4_zhongwen_wendang-2024.3.4.0.dist-info/WHEEL
scapy_2_4_zhongwen_wendang-2024.3.4.0.dist-info/entry_points.txt
scapy_2_4_zhongwen_wendang-2024.3.4.0.dist-info/top_level.txt
scapy_2_4_zhongwen_wendang-2024.3.4.0.dist-info/RECORD
